<?xml version="1.0" encoding="UTF-8"?><oai_dc:dc xmlns:oai_dc="http://www.openarchives.org/OAI/2.0/oai_dc/" xmlns:dc="http://purl.org/dc/elements/1.1/" xmlns:xsi="http://www.w3.org/2001/XMLSchema-instance" xsi:schemaLocation="http://www.openarchives.org/OAI/2.0/oai_dc/ http://www.openarchives.org/OAI/2.0/oai_dc.xsd"><dc:identifier>http://zaguan.unizar.es/record/12025</dc:identifier><dc:language>spa</dc:language><dc:creator>Lucea López, Elena</dc:creator><dc:creator>Gimeno Monterde, Chabier</dc:creator><dc:title>Familias Sin Hogar</dc:title><dc:description>Este Trabajo Fin de Grado pretende acercar al lector del mismo la incipiente realidad de muchas familias en nuestro país, y más concretamente en la ciudad de Zaragoza. Esta investigación parte de los orígenes de este fenómeno social, sus causas, consecuencias y aquellos recursos que atienden a las familias afectadas, las "Familias Sin Hogar".</dc:description><dc:publisher>Universidad de Zaragoza</dc:publisher><dc:identifier>TAZ-TFG-2013-755</dc:identifier><dc:identifier>oai:zaguan.unizar.es:12025</dc:identifier><dc:date>2013</dc:date></oai_dc:dc>