<?xml version="1.0" encoding="UTF-8"?><oai_dc:dc xmlns:oai_dc="http://www.openarchives.org/OAI/2.0/oai_dc/" xmlns:dc="http://purl.org/dc/elements/1.1/" xmlns:xsi="http://www.w3.org/2001/XMLSchema-instance" xsi:schemaLocation="http://www.openarchives.org/OAI/2.0/oai_dc/ http://www.openarchives.org/OAI/2.0/oai_dc.xsd"><dc:identifier>http://zaguan.unizar.es/record/13030</dc:identifier><dc:language>spa</dc:language><dc:creator>Mayobre Gallego, Roberto</dc:creator><dc:creator>Pérez Forniés, Claudia</dc:creator><dc:title>La situación actual de la Defensa en España: crisis aguda o herencia crónica</dc:title><dc:description>El presente trabajo aborda la situación actual de la Defensa en España y cómo se ha visto afectada por los recortes producidos a raíz de la crisis de 2008, partiendo del proceso de transformación de las Fuerzas Armadas y el análisis de la evolución de los presupuestos de Defensa, prestando especial atención a los Programas Especiales de Armamento (PEAs).</dc:description><dc:publisher>Universidad de Zaragoza</dc:publisher><dc:identifier>TAZ-TFM-2013-1156</dc:identifier><dc:identifier>oai:zaguan.unizar.es:13030</dc:identifier><dc:date>2013</dc:date></oai_dc:dc>