<?xml version="1.0" encoding="UTF-8"?><oai_dc:dc xmlns:oai_dc="http://www.openarchives.org/OAI/2.0/oai_dc/" xmlns:dc="http://purl.org/dc/elements/1.1/" xmlns:xsi="http://www.w3.org/2001/XMLSchema-instance" xsi:schemaLocation="http://www.openarchives.org/OAI/2.0/oai_dc/ http://www.openarchives.org/OAI/2.0/oai_dc.xsd"><dc:identifier>http://zaguan.unizar.es/record/47373</dc:identifier><dc:language>spa</dc:language><dc:creator>Salanova Cortés, Álvaro</dc:creator><dc:creator>Rodríguez García, José Luis</dc:creator><dc:title>Reformarnos para deformar. Poder y ética en el último Foucault</dc:title><dc:description>Después de desarrollar su concepción del poder, Michel Foucault recibió numerosas críticas que anulaban en esta teoría la capacidad de emancipación que se había defendido años atrás. A pesar de haber podido ser una teoría pesimista en su principio, pues se renuncia a la liberación total y, en cierta forma, utópica que había caracterizado a teorías anteriores, Foucault continuó sus estudios en un intento de crear nuevas relaciones de poder que engordasen la resistencia, recurriendo en gran medida a los textos de los antiguos griegos que entendían la filosofía como arte de vivir. El objetivo de este trabajo es defender esta teoría del poder ante ciertas críticas realizadas para, a continuación, analizar esas propuestas de Foucault realizando una valoración de su posibilidad en el presente.</dc:description><dc:publisher>Universidad de Zaragoza</dc:publisher><dc:identifier>TAZ-TFG-2015-2945</dc:identifier><dc:identifier>oai:zaguan.unizar.es:47373</dc:identifier><dc:date>2015</dc:date></oai_dc:dc>