<?xml version="1.0" encoding="UTF-8"?><oai_dc:dc xmlns:oai_dc="http://www.openarchives.org/OAI/2.0/oai_dc/" xmlns:dc="http://purl.org/dc/elements/1.1/" xmlns:xsi="http://www.w3.org/2001/XMLSchema-instance" xsi:schemaLocation="http://www.openarchives.org/OAI/2.0/oai_dc/ http://www.openarchives.org/OAI/2.0/oai_dc.xsd"><dc:identifier>http://zaguan.unizar.es/record/30983</dc:identifier><dc:language>spa</dc:language><dc:creator>Bardina Torres, Marta</dc:creator><dc:creator>Espeitx Bernat, Elena</dc:creator><dc:title>La adherencia a un programa de ejercicio físico con mujeres con depresión leve, una propuesta de intervención.</dc:title><dc:description>La siguiente propuesta de intervención va dirigida a mujeres de entre 45 y 65 años, que presentan síntomas de depresión leve o moderada de la provincia de Zaragoza. Se procederá a trabajar la motivación intrínseca para conseguir una adherencia a un programa de ejercicio físico, a través del cual se pretende que los niveles de depresión disminuyan a corto y a largo plazo. Se evaluarán los niveles de depresión, la motivación, el estado de ánimo, las barreras percibidas, etc. en resumen se procederá a evaluar aspectos pertinentes en relación a la problemática de las mujeres.</dc:description><dc:publisher>Universidad de Zaragoza</dc:publisher><dc:identifier>TAZ-TFG-2014-2567</dc:identifier><dc:identifier>oai:zaguan.unizar.es:30983</dc:identifier><dc:date>2014</dc:date></oai_dc:dc>