<?xml version="1.0" encoding="UTF-8"?><oai_dc:dc xmlns:oai_dc="http://www.openarchives.org/OAI/2.0/oai_dc/" xmlns:dc="http://purl.org/dc/elements/1.1/" xmlns:xsi="http://www.w3.org/2001/XMLSchema-instance" xsi:schemaLocation="http://www.openarchives.org/OAI/2.0/oai_dc/ http://www.openarchives.org/OAI/2.0/oai_dc.xsd"><dc:identifier>http://zaguan.unizar.es/record/14627</dc:identifier><dc:language>spa</dc:language><dc:creator>Casasús Giménez, Carmen</dc:creator><dc:creator>Civiac Garcés, Patricia</dc:creator><dc:creator>Marí Klose, Pau</dc:creator><dc:title>Vivir a la intemperie. Personas sin hogar en Zaragoza</dc:title><dc:description>Este trabajo recoge el análisis de diversas entrevistas realizadas a personas sin hogar que se encuentran actualmente en la ciudad de Zaragoza.</dc:description><dc:publisher>Universidad de Zaragoza</dc:publisher><dc:identifier>TAZ-TFG-2014-727</dc:identifier><dc:identifier>oai:zaguan.unizar.es:14627</dc:identifier><dc:date>2014</dc:date></oai_dc:dc>