<?xml version="1.0" encoding="UTF-8"?><oai_dc:dc xmlns:oai_dc="http://www.openarchives.org/OAI/2.0/oai_dc/" xmlns:dc="http://purl.org/dc/elements/1.1/" xmlns:xsi="http://www.w3.org/2001/XMLSchema-instance" xsi:schemaLocation="http://www.openarchives.org/OAI/2.0/oai_dc/ http://www.openarchives.org/OAI/2.0/oai_dc.xsd"><dc:identifier>http://zaguan.unizar.es/record/14608</dc:identifier><dc:language>spa</dc:language><dc:creator>Casasús Valtueña, Miguel</dc:creator><dc:creator>Paricio Royo, Javier</dc:creator><dc:title>Identificación de los problemas de comprensión del tiempo histórico. Una intervención educativa</dc:title><dc:description>Este documento presenta una actividad educativa innovadora para el aprendizaje histórico en los estudiantes de 10 a 11 años. 	La concepción cronológica del alumnado es de gran dificultad, tal como diferentes autores desarrollan, para articular los hechos históricos. Tras el análisis de las teorías actuales, propongo y realizo una intervención educativa que a través de la manipulación física en una gran línea del tiempo, es capaz de determinar los problemas de la comprensión cronológica que impiden crear un marco cronológico mental en el educando.  A pesar de que la actividad fue un éxito desde el punto de vista de la implicación y la recogida de datos, los resultados de esta intervención vuelven a demostrar que las dificultades para construir un modelo mental cronológico, persisten.</dc:description><dc:publisher>Universidad de Zaragoza</dc:publisher><dc:identifier>TAZ-TFG-2014-715</dc:identifier><dc:identifier>oai:zaguan.unizar.es:14608</dc:identifier><dc:date>2014</dc:date></oai_dc:dc>