<?xml version="1.0" encoding="UTF-8"?><oai_dc:dc xmlns:oai_dc="http://www.openarchives.org/OAI/2.0/oai_dc/" xmlns:dc="http://purl.org/dc/elements/1.1/" xmlns:xsi="http://www.w3.org/2001/XMLSchema-instance" xsi:schemaLocation="http://www.openarchives.org/OAI/2.0/oai_dc/ http://www.openarchives.org/OAI/2.0/oai_dc.xsd"><dc:identifier>http://zaguan.unizar.es/record/8513</dc:identifier><dc:language>spa</dc:language><dc:creator>Palacios Calvo, Juan Carlos</dc:creator><dc:creator>Fernández Olmos, Marta</dc:creator><dc:title>La internacionalización de la empresa</dc:title><dc:description>Revisión de literatura que analiza la internacionalización de las empresas. La revisión, capítulo de una futura tesis sobre esta materia, repasa algunas de las teorías sobre internacionalización de las empresas más citadas en las últimos décadas, desde la perspectiva macroeconómica y la microeconómica. Este trabajo muestra que no hay un cuerpo único para su estudio y comprensión, lo que ha dificultado y dificulta la propia investigación empírica del comportamiento empresarial en su actividad exterior.</dc:description><dc:publisher>Universidad de Zaragoza</dc:publisher><dc:identifier>TAZ-TFM-2012-557</dc:identifier><dc:identifier>oai:zaguan.unizar.es:8513</dc:identifier><dc:date>2012</dc:date></oai_dc:dc>