<?xml version="1.0" encoding="UTF-8"?><oai_dc:dc xmlns:oai_dc="http://www.openarchives.org/OAI/2.0/oai_dc/" xmlns:dc="http://purl.org/dc/elements/1.1/" xmlns:xsi="http://www.w3.org/2001/XMLSchema-instance" xsi:schemaLocation="http://www.openarchives.org/OAI/2.0/oai_dc/ http://www.openarchives.org/OAI/2.0/oai_dc.xsd"><dc:identifier>http://zaguan.unizar.es/record/47163</dc:identifier><dc:language>spa</dc:language><dc:creator>García Crespo, Enrique</dc:creator><dc:creator>Lambán Castillo, María Pilar</dc:creator><dc:title>Trabajo Fin de Máster</dc:title><dc:description>La elaboración del trabajo de fin de Máster constituye, por un lado, un ejercicio sobre la concepción de la docencia y todo lo que su práctica conlleva, y por otro lado supone un elemento fundamental para autoevaluarnos como docentes después de este año académico.</dc:description><dc:publisher>Universidad de Zaragoza</dc:publisher><dc:identifier>TAZ-TFM-2015-285</dc:identifier><dc:identifier>oai:zaguan.unizar.es:47163</dc:identifier><dc:date>2015</dc:date></oai_dc:dc>