<?xml version="1.0" encoding="UTF-8"?><oai_dc:dc xmlns:oai_dc="http://www.openarchives.org/OAI/2.0/oai_dc/" xmlns:dc="http://purl.org/dc/elements/1.1/" xmlns:xsi="http://www.w3.org/2001/XMLSchema-instance" xsi:schemaLocation="http://www.openarchives.org/OAI/2.0/oai_dc/ http://www.openarchives.org/OAI/2.0/oai_dc.xsd"><dc:identifier>http://zaguan.unizar.es/record/8899</dc:identifier><dc:language>spa</dc:language><dc:creator>García Mártínez, Belén</dc:creator><dc:creator>Pérez Marín, Carmen</dc:creator><dc:creator>Villar Rivacoba, José Ángel</dc:creator><dc:title>Caracterización radiológica de muestras de suelo: toma de muestra, conservación y preparación, análisis por espectrometría gamma, determinación del índice de actividad beta total y procedimiento de separación radiológica para la determinación del Sr90.</dc:title><dc:description>El objetivo principal de este Trabajo Fin de Máster ha sido la caracterización radiológica de muestras de suelo. Las etapas que se han seguido han sido: toma de muestra, conservación y preparación, análisis por espectrometría gamma, determinación del índice de actividad beta total y procedimiento de separación radioquímica para la determinación del isótopo Sr90.  Se han utilizado los equipos para la realización del análisis por espectrometría gamma, detector de germanio, y para la determinación del índice de actividad beta total, contador proporcional alfa-beta. Se ha llevado a cabo la revisión y optimización de los procedimientos de toma de muestra y de separaciones radioquímicas. Por último, se ha realizado el análisis de resultados y extraído conclusiones.</dc:description><dc:publisher>Universidad de Zaragoza</dc:publisher><dc:identifier>TAZ-TFM-2012-740</dc:identifier><dc:identifier>oai:zaguan.unizar.es:8899</dc:identifier><dc:date>2012</dc:date></oai_dc:dc>