<?xml version="1.0" encoding="UTF-8"?><oai_dc:dc xmlns:oai_dc="http://www.openarchives.org/OAI/2.0/oai_dc/" xmlns:dc="http://purl.org/dc/elements/1.1/" xmlns:xsi="http://www.w3.org/2001/XMLSchema-instance" xsi:schemaLocation="http://www.openarchives.org/OAI/2.0/oai_dc/ http://www.openarchives.org/OAI/2.0/oai_dc.xsd"><dc:identifier>http://zaguan.unizar.es/record/8089</dc:identifier><dc:language>spa</dc:language><dc:creator>García Vicente, Cristina</dc:creator><dc:creator>Gonzalez Vera, María Pilar</dc:creator><dc:title>Trabajo Fin de Máster - Modalidad A</dc:title><dc:description>El presente documento pretender ser una compilación de todo lo aprendido a lo largo del Máster y en especial de los trabajos que mayor relevancia han tenido para nuestra futura labor como docentes de Lengua Inglesa.</dc:description><dc:publisher>Universidad de Zaragoza</dc:publisher><dc:identifier>TAZ-TFM-2012-197</dc:identifier><dc:identifier>oai:zaguan.unizar.es:8089</dc:identifier><dc:date>2012</dc:date></oai_dc:dc>