<?xml version="1.0" encoding="UTF-8"?><oai_dc:dc xmlns:oai_dc="http://www.openarchives.org/OAI/2.0/oai_dc/" xmlns:dc="http://purl.org/dc/elements/1.1/" xmlns:xsi="http://www.w3.org/2001/XMLSchema-instance" xsi:schemaLocation="http://www.openarchives.org/OAI/2.0/oai_dc/ http://www.openarchives.org/OAI/2.0/oai_dc.xsd"><dc:identifier>http://zaguan.unizar.es/record/10979</dc:identifier><dc:language>spa</dc:language><dc:creator>Gómez Martín, Cristina</dc:creator><dc:creator>Julián Soriano, Vanessa</dc:creator><dc:creator>Sanz Sánchez, Nuria</dc:creator><dc:creator>Marco Fabre, Miguel</dc:creator><dc:title>Las personas sin hogar en Zaragoza. Análisis de los recursos sociales</dc:title><dc:description>El trabajo fin de grado consiste en el análisis de la población de las personas sin hogar de la ciudad de Zaragoza, así como de los recursos sociales existentes destinados a esta población, tratando de determinar la situación de los mismos, su suficiencia y su adecuación a las características de esta población.</dc:description><dc:publisher>Universidad de Zaragoza</dc:publisher><dc:identifier>TAZ-TFG-2013-414</dc:identifier><dc:identifier>oai:zaguan.unizar.es:10979</dc:identifier><dc:date>2013</dc:date></oai_dc:dc>